DDPCL/__init__.py
DDPCL/Labeler/Labeler.py
DDPCL/Labeler/__init__.py
DDPCL/ProbabilitiesChecker/ProbabilitiesChecker.py
DDPCL/ProbabilitiesChecker/__init__.py
DDPCL/util_functions/__init__.py
DDPCL/util_functions/util_functions.py
DDPCL-1.0.0.3.dist-info/LICENSE
DDPCL-1.0.0.3.dist-info/METADATA
DDPCL-1.0.0.3.dist-info/WHEEL
DDPCL-1.0.0.3.dist-info/top_level.txt
DDPCL-1.0.0.3.dist-info/RECORD
