Metadata-Version: 2.1
Name: DDPCL
Version: 1.0.0.3
Home-page: http://pypi.python.org/pypi/DDPCL/
Author: Anthony SIAMPIRINGUE
Author-email: anthony.siampiringue@epita.fr
License: MIT
Keywords: drift detection CV bayesian recognition autolabeling
License-File: LICENSE
Requires-Dist: opencv-python
Requires-Dist: pandas
Requires-Dist: numpy
Requires-Dist: scipy
Requires-Dist: scikit-learn
Requires-Dist: shutils
Requires-Dist: uuid
Requires-Dist: pillow
Requires-Dist: face-recognition
Requires-Dist: matplotlib
